services_communicator/__init__.py
services_communicator/admin.py
services_communicator/apps.py
services_communicator/communicator.py
services_communicator/exceptions.py
services_communicator/models.py
services_communicator/urls.py
services_communicator/views.py
services_communicator/migrations/0001_initial.py
services_communicator/migrations/__init__.py
services_communicator/test_utils/__init__.py
services_communicator/test_utils/test_app/__init__.py
services_communicator/test_utils/test_app/admin.py
services_communicator/test_utils/test_app/apps.py
services_communicator/test_utils/test_app/models.py
services_communicator/test_utils/test_app/migrations/__init__.py
services_communicator-0.3.0.dist-info/AUTHORS.rst
services_communicator-0.3.0.dist-info/LICENSE
services_communicator-0.3.0.dist-info/METADATA
services_communicator-0.3.0.dist-info/WHEEL
services_communicator-0.3.0.dist-info/top_level.txt
services_communicator-0.3.0.dist-info/RECORD
