Metadata-Version: 2.1
Name: services-communicator
Version: 0.3.0
Summary: Communicator for internal services
Home-page: https://github.com/eshafik/services_communicator
Author: MSI Shafik
Author-email: shafik.te@gmail.com
License: MIT
Keywords: services_communicator
Platform: UNKNOWN
Classifier: Development Status :: 3 - Alpha
Classifier: Framework :: Django :: 2.1
Classifier: Intended Audience :: Developers
Classifier: License :: OSI Approved :: BSD License
Classifier: Natural Language :: English
Classifier: Programming Language :: Python :: 2
Classifier: Programming Language :: Python :: 2.7
Classifier: Programming Language :: Python :: 3
Classifier: Programming Language :: Python :: 3.5
Classifier: Programming Language :: Python :: 3.6
Requires-Dist: django-model-utils (>=2.0)
